mongodb/__init__.py
mongodb/connectionparams.py
mongodb/dbmanager.py
mongodb/dbmanagerprotocol.py
mongodb/ephemeralmongodbcontext.py
mongodb/ephemeralmongodbcontextbuilder.py
mongodb/filesmanager.py
ephemerals_mongodb-1.0.1.dist-info/LICENSE.md
ephemerals_mongodb-1.0.1.dist-info/METADATA
ephemerals_mongodb-1.0.1.dist-info/WHEEL
ephemerals_mongodb-1.0.1.dist-info/top_level.txt
ephemerals_mongodb-1.0.1.dist-info/RECORD
