Metadata-Version: 2.1
Name: ephemerals-mongodb
Version: 1.0.1
Summary: Ephemeral MongoDB Context Helper.
Home-page: https://github.com/paranoid-software/ephemerals.py/tree/main/mongodb
Author: Paranoid Software
Author-email: info@paranoid.software
License: MIT
Classifier: Programming Language :: Python :: 3
Classifier: Programming Language :: Python :: 3.9
Classifier: Operating System :: OS Independent
Requires-Python: >=3.6
License-File: LICENSE.md
Requires-Dist: pymongo (>=4.0.1)
